jupyterlab_telemetry/__init__.py
jupyterlab_telemetry/_version.py
jupyterlab_telemetry/handlers.py
jupyterlab_telemetry/tests/__init__.py
jupyterlab_telemetry/tests/test_handlers.py
jupyterlab_telemetry-1.0.3.data/data/etc/jupyter/jupyter_notebook_config.d/jupyterlab_telemetry.json
jupyterlab_telemetry-1.0.3.data/data/etc/jupyter/jupyter_server_config.d/jupyterlab_telemetry.json
jupyterlab_telemetry-1.0.3.dist-info/LICENSE
jupyterlab_telemetry-1.0.3.dist-info/METADATA
jupyterlab_telemetry-1.0.3.dist-info/WHEEL
jupyterlab_telemetry-1.0.3.dist-info/top_level.txt
jupyterlab_telemetry-1.0.3.dist-info/RECORD
